{
	"info": {
		"_postman_id": "7397beca-1b36-413e-bb5e-0bebc6c479fd",
		"name": "bot parawisata",
		"schema": "https://schema.getpostman.com/json/collection/v2.1.0/collection.json",
		"_exporter_id": "29695453"
	},
	"item": [
		{
			"name": "promt",
			"request": {
				"method": "POST",
				"header": [],
				"body": {
					"mode": "raw",
					"raw": "{\"message\":\"sebutkan parawisata yang ada di pekanbaru\",\"sessionId\":\"u3\"}\r\n",
					"options": {
						"raw": {
							"language": "json"
						}
					}
				},
				"url": {
					"raw": "https://deeplearning.pcr.ac.id/webhook-test/bot-parawisata-pekanbaru",
					"protocol": "https",
					"host": [
						"deeplearning",
						"pcr",
						"ac",
						"id"
					],
					"path": [
						"webhook-test",
						"bot-parawisata-pekanbaru"
					]
				}
			},
			"response": []
		}
	]
}